rocket/__init__.py
rocket/rocket.py
rocket_seds_lab3_meriem_terki-0.3.dist-info/LICENSE.txt
rocket_seds_lab3_meriem_terki-0.3.dist-info/METADATA
rocket_seds_lab3_meriem_terki-0.3.dist-info/WHEEL
rocket_seds_lab3_meriem_terki-0.3.dist-info/top_level.txt
rocket_seds_lab3_meriem_terki-0.3.dist-info/RECORD
