Metadata-Version: 2.1
Name: rocket-seds-lab3-meriem-terki
Version: 0.3
Summary: A package to simulate rockets and shuttles.
Author: Meriem Terki
License: MIT
License-File: LICENSE.txt
